flyerops/__init__.py
flyerops/mlops/__init__.py
flyerops/mlops/pipelines/__init__.py
flyerops/mlops/pipelines/pipeline.py
flyerops/utils/__init__.py
flyerops/utils/utils.py
flyerops-0.1.6.dist-info/METADATA
flyerops-0.1.6.dist-info/WHEEL
flyerops-0.1.6.dist-info/top_level.txt
flyerops-0.1.6.dist-info/RECORD
